market_clock/__init__.py
market_clock/get_market_info.py
market_clock-0.3.1.dist-info/METADATA
market_clock-0.3.1.dist-info/WHEEL
market_clock-0.3.1.dist-info/entry_points.txt
market_clock-0.3.1.dist-info/licenses/LICENSE
market_clock-0.3.1.dist-info/RECORD
