Metadata-Version: 2.4
Name: market-clock
Version: 0.3.1
Summary: Market clock in your terminal
Project-URL: Repository, https://github.com/plwg/market-clock
Author-email: plwg <56353330+plwg@users.noreply.github.com>
License-Expression: MIT
License-File: LICENSE
Keywords: cli,clock,exchange,stock market,trading
Classifier: Development Status :: 4 - Beta
Classifier: Environment :: Console
Classifier: Operating System :: OS Independent
Classifier: Programming Language :: Python :: 3
Requires-Python: >=3.10
Requires-Dist: blessed>=1.20.0
Requires-Dist: tzdata>=2025.2
